thriftcli/__init__.py
thriftcli/__main__.py
thriftcli/java_thrift_request_body_converter.py
thriftcli/json_request_body_converter.py
thriftcli/request_body_converter.py
thriftcli/thrift_argument_converter.py
thriftcli/thrift_cli.py
thriftcli/thrift_cli_error.py
thriftcli/thrift_executor.py
thriftcli/thrift_parse_result.py
thriftcli/thrift_parser.py
thriftcli/thrift_service.py
thriftcli/thrift_struct.py
thriftcli/thrift_zookeeper_resolver.py
thriftcli/tls_transport.py
thriftcli/transport.py
thriftcli-1.5.dist-info/LICENSE.txt
thriftcli-1.5.dist-info/METADATA
thriftcli-1.5.dist-info/NOTICE.txt
thriftcli-1.5.dist-info/WHEEL
thriftcli-1.5.dist-info/entry_points.txt
thriftcli-1.5.dist-info/top_level.txt
thriftcli-1.5.dist-info/RECORD
