Metadata-Version: 2.1
Name: thriftcli
Version: 1.5
Summary: Thrift CLI
Home-page: UNKNOWN
Author: Neel Virdy
Author-email: UNKNOWN
License: UNKNOWN
Platform: UNKNOWN
Requires-Dist: kazoo
Requires-Dist: mock
Requires-Dist: requests-kerberos
Requires-Dist: thrift
Requires-Dist: twitter.common.rpc (==0.3.9)
Requires-Dist: coverage
